aioengine/__init__.py
aioengine/exceptions.py
aioengine/engines/__init__.py
aioengine/engines/google/__init__.py
aioengine/engines/google/google.py
aioengine/engines/google/network.py
aioengine/engines/google/parser.py
aioengine_python-0.0.4.dist-info/METADATA
aioengine_python-0.0.4.dist-info/WHEEL
aioengine_python-0.0.4.dist-info/top_level.txt
aioengine_python-0.0.4.dist-info/RECORD
