Metadata-Version: 2.1
Name: aioengine-python
Version: 0.0.4
Summary: Asynchronous engine for search engines
Home-page: https://github.com/KissmeBro/aioengine
Author: stone
Author-email: manybot.00@gmail.com
Classifier: Programming Language :: Python :: 3
Classifier: Programming Language :: Python :: 3.8
Classifier: License :: OSI Approved :: MIT License
Requires-Python: >=3.6
Requires-Dist: aiohttp
Requires-Dist: rich
Requires-Dist: pydantic
